serverchain/__init__.py
serverchain/__version__.py
serverchain/channel.py
serverchain/main.py
test/__init__.py
test/test.py
serverchain-0.1.1.dist-info/LICENSE
serverchain-0.1.1.dist-info/METADATA
serverchain-0.1.1.dist-info/WHEEL
serverchain-0.1.1.dist-info/top_level.txt
serverchain-0.1.1.dist-info/RECORD
