Metadata-Version: 2.1
Name: serverchain
Version: 0.1.1
Summary: unofficial sdk for serverchain by anysoft.
Home-page: https://github.com/anysoft/serverchain
Author: anysoft
Author-email: anysoft@yeah.net
License: MIT
Classifier: License :: OSI Approved :: MIT License
Classifier: Programming Language :: Python
Classifier: Programming Language :: Python :: 3
Classifier: Programming Language :: Python :: 3.6
Classifier: Programming Language :: Python :: Implementation :: CPython
Classifier: Programming Language :: Python :: Implementation :: PyPy
Requires-Python: >=3.6.0
License-File: LICENSE
